wechat/__init__.py
wechat/crypt.py
wechat/enterprise.py
wechat/models.py
wechat/official.py
wechat3-0.5.0.dist-info/LICENSE
wechat3-0.5.0.dist-info/METADATA
wechat3-0.5.0.dist-info/WHEEL
wechat3-0.5.0.dist-info/top_level.txt
wechat3-0.5.0.dist-info/RECORD
