Metadata-Version: 2.1
Name: wechat3
Version: 0.5.0
Summary: Wechat Python SDK
Home-page: https://github.com/tclh123/wechat
Author: jeff kit
Author-email: bbmyth@gmail.com
Maintainer: Harry Lee
Maintainer-email: tclh123@gmail.com
License: GPLv3
Keywords: wechat,SDK
Platform: UNKNOWN
Classifier: Programming Language :: Python
Classifier: Programming Language :: Python :: 2.7
Classifier: Programming Language :: Python :: 3
Classifier: Programming Language :: Python :: 3.4
Classifier: Programming Language :: Python :: 3.5
Classifier: Programming Language :: Python :: 3.6
Classifier: Programming Language :: Python :: 3.7
Classifier: Development Status :: 5 - Production/Stable
Classifier: Environment :: Console
Classifier: Intended Audience :: Developers
Classifier: License :: OSI Approved :: GNU General Public License v3 (GPLv3)
Classifier: Operating System :: POSIX :: Linux
Classifier: Topic :: Software Development :: Libraries :: Python Modules
Requires-Dist: requests
Requires-Dist: cryptography
